activity_tracker/__init__.py
activity_tracker/__version__.py
activity_tracker/admin.py
activity_tracker/admin_mixins.py
activity_tracker/apps.py
activity_tracker/constants.py
activity_tracker/context.py
activity_tracker/diff.py
activity_tracker/drf.py
activity_tracker/drf_mixins.py
activity_tracker/helpers.py
activity_tracker/middleware.py
activity_tracker/model_signals.py
activity_tracker/models.py
activity_tracker/services.py
activity_tracker/settings.py
activity_tracker/signals.py
activity_tracker/utils.py
activity_tracker/migrations/0001_initial.py
activity_tracker/migrations/__init__.py
django_system_audit-0.1.1.dist-info/licenses/LICENSE
django_system_audit-0.1.1.dist-info/METADATA
django_system_audit-0.1.1.dist-info/WHEEL
django_system_audit-0.1.1.dist-info/top_level.txt
django_system_audit-0.1.1.dist-info/RECORD
