Metadata-Version: 2.4
Name: django-system-audit
Version: 0.1.1
Summary: Explicit, intent-aware audit trail library for Django and Django REST Framework
Author-email: Rajat Jog <rajatjog1294@gmail.com>
License: MIT
Project-URL: Homepage, https://github.com/RJ-Gamer/django-activity-tracker
Requires-Python: >=3.9
License-File: LICENSE
Requires-Dist: Django>=3.2
Dynamic: license-file
